[{"judul": "Golkar Undang PPP Halal Bihalal: Kenang Koalisi Indonesia Bersatu", "kategori": "Politik", "waktu_publish": "Senin , 15 Apr 2024, 20:26 WIB", "waktu_scraping": "15-04-2024 20:31:58"}, {"judul": "Nasdem Terbuka Atas Peluang Usung Anies di Pilgub Jakarta 2024", "kategori": "Politik", "waktu_publish": "Senin , 15 Apr 2024, 20:11 WIB", "waktu_scraping": "15-04-2024 20:31:58"}, {"judul": "Anies dan Muhaimin Belum Bertemu Surya Paloh di Momen Idulfitri\u00a0Tahun Ini", "kategori": "Politik", "waktu_publish": "Senin , 15 Apr 2024, 20:08 WIB", "waktu_scraping": "15-04-2024 20:31:58"}, {"judul": "Pertemuan Megawati dengan Prabowo Diprediksi Tunggu Putusan MK", "kategori": "Politik", "waktu_publish": "Senin , 15 Apr 2024, 16:00 WIB", "waktu_scraping": "15-04-2024 20:31:58"}, {"judul": "Kemungkinan Gabungnya PDIP ke Koalisi, Idrus Marham: Ada Hitung-Hitungannya", "kategori": "Politik", "waktu_publish": "Senin , 15 Apr 2024, 11:05 WIB", "waktu_scraping": "15-04-2024 20:31:58"}, {"judul": "Karena Hal Sepele, Pria di Bandung Pukuli Anak Tirinya Berusia 4 Tahun Hingga Tewas", "kategori": "Hukum", "waktu_publish": "Ahad , 07 Apr 2024, 20:19 WIB", "waktu_scraping": "15-04-2024 20:31:58"}, {"judul": "PRIDE: Kesaksian 4 Menteri di MK Patahkan Tuduhan Kecurangan Politisasi Bansos", "kategori": "Hukum", "waktu_publish": "Ahad , 07 Apr 2024, 12:36 WIB", "waktu_scraping": "15-04-2024 20:31:58"}, {"judul": "LSM CERI Ungkap Kejanggalan Pemeriksaan RBS oleh Kejagung di Kasus Korupsi PT Timah", "kategori": "Hukum", "waktu_publish": "Ahad , 07 Apr 2024, 04:32 WIB", "waktu_scraping": "15-04-2024 20:31:58"}, {"judul": "Mantan Penyidik Desak Pimpinan KPK Serius Tolak Wacana Penggabungan dengan Ombudsman", "kategori": "Hukum", "waktu_publish": "Sabtu , 06 Apr 2024, 17:19 WIB", "waktu_scraping": "15-04-2024 20:31:58"}, {"judul": "KPK Segera Terbitkan Sprindik Baru Eddy Hiariej", "kategori": "Hukum", "waktu_publish": "Sabtu , 06 Apr 2024, 14:19 WIB", "waktu_scraping": "15-04-2024 20:31:58"}, {"judul": "Jago\u00a0 Tari, Ayo Daftarkan Dirimu\u00a0Program Beasiswa dari Cyber University", "kategori": "Dunia Kampus", "waktu_publish": "Ahad , 07 Apr 2024, 13:15 WIB", "waktu_scraping": "15-04-2024 20:31:58"}, {"judul": "Penutupan Pilmapres PTMA, Septa Candra: Pembinaan Mahasiswa tak Bisa Dilakukan Instan", "kategori": "Dunia Kampus", "waktu_publish": "Ahad , 07 Apr 2024, 12:30 WIB", "waktu_scraping": "15-04-2024 20:31:58"}, {"judul": "Rektor Unhas Tegaskan tak Ada Orang Dalam di SNPMB", "kategori": "Dunia Kampus", "waktu_publish": "Sabtu , 06 Apr 2024, 22:13 WIB", "waktu_scraping": "15-04-2024 20:31:58"}, {"judul": "Ini Beberapa Keuntungan Memiliki Perpustakaan Digital Bagi Kampus", "kategori": "Pendidikan", "waktu_publish": "Sabtu , 06 Apr 2024, 14:25 WIB", "waktu_scraping": "15-04-2024 20:31:58"}, {"judul": "Dijamin Kamu Nggak Nyesel, Pilih Kuliah Sarjana Jalur Beasiswa di Universitas Nusa Mandiri", "kategori": "Pendidikan", "waktu_publish": "Sabtu , 06 Apr 2024, 12:41 WIB", "waktu_scraping": "15-04-2024 20:31:58"}, {"judul": "Bentrok TNI-Polri Kembali Terjadi, Dewan Ingatkan Bahaya Ego Sektoral", "kategori": "Umum", "waktu_publish": "Senin , 15 Apr 2024, 20:22 WIB", "waktu_scraping": "15-04-2024 20:31:58"}, {"judul": "Jasamarga: Senin Masih Terjadi Arus Balik di Tol Padaleunyi-Cipularang", "kategori": "Umum", "waktu_publish": "Senin , 15 Apr 2024, 20:14 WIB", "waktu_scraping": "15-04-2024 20:31:58"}, {"judul": "Kapolri Pastikan Semua Pihak Bersinergi Beri Pelayanan Terbaik Arus Balik Lebaran", "kategori": "Umum", "waktu_publish": "Senin , 15 Apr 2024, 19:32 WIB", "waktu_scraping": "15-04-2024 20:31:58"}, {"judul": "Kemenkes Catat 475 Kematian Akibat DBD Hingga Pekan Ke-15 2024", "kategori": "Umum", "waktu_publish": "Senin , 15 Apr 2024, 18:39 WIB", "waktu_scraping": "15-04-2024 20:31:58"}, {"judul": "Rumah Pemenangan Prabowo-Gibran Kemalingan, TV 32 Inci Raib", "kategori": "Umum", "waktu_publish": "Senin , 15 Apr 2024, 18:26 WIB", "waktu_scraping": "15-04-2024 20:31:58"}, {"judul": "Kejagung Bertanya ke KPK: Tangani Kasus LPEI yang Mana?", "kategori": "Terpopuler", "waktu_publish": "Rabu , 20 Mar 2024, 18:58 WIB", "waktu_scraping": "15-04-2024 20:31:58"}, {"judul": "Israel Kini Gunakan Kelaparan Sebagai Senjata Membunuh Warga Palestina di Gaza", "kategori": "Terpopuler", "waktu_publish": "Rabu , 20 Mar 2024, 06:03 WIB", "waktu_scraping": "15-04-2024 20:31:58"}, {"judul": "Kala DPR Isyaratkan Ogah Pindah, Tapi Pemerintah tak Ingin Sendirian di Ibu Kota Nusantara", "kategori": "Terpopuler", "waktu_publish": "Selasa , 19 Mar 2024, 06:37 WIB", "waktu_scraping": "15-04-2024 20:31:58"}, {"judul": "Miras Berlabel Halal Muncul Lagi, Cek Faktanya", "kategori": "Terpopuler", "waktu_publish": "Rabu , 03 Mar 2021, 08:09 WIB", "waktu_scraping": "15-04-2024 20:31:58"}, {"judul": "Hoaks Catut KH Maruf Amin di Tengah Isu Investasi Miras", "kategori": "Terpopuler", "waktu_publish": "Senin , 01 Mar 2021, 18:00 WIB", "waktu_scraping": "15-04-2024 20:31:58"}, {"judul": "Jika Vaksinasi Gagal, Pemerintah tak Beri Kompensasi?", "kategori": "Terpopuler", "waktu_publish": "Sabtu , 27 Feb 2021, 07:33 WIB", "waktu_scraping": "15-04-2024 20:31:58"}, {"judul": "Pigai, Papua, Abu Janda, dan Bahaya Rasialisme", "kategori": "Terpopuler", "waktu_publish": "Ahad , 31 Jan 2021, 20:21 WIB", "waktu_scraping": "15-04-2024 20:31:58"}, {"judul": "Blak-blakan Kasus Jilbab SMKN 2 Padang", "kategori": "Terpopuler", "waktu_publish": "Kamis , 28 Jan 2021, 19:17 WIB", "waktu_scraping": "15-04-2024 20:31:58"}, {"judul": "Apa Dalil Banyak Ulama Wafat, Kiamat Sudah Dekat?", "kategori": "Terpopuler", "waktu_publish": "Rabu , 27 Jan 2021, 11:14 WIB", "waktu_scraping": "15-04-2024 20:31:58"}]